fujson.py
fujson-0.1.1.dist-info/METADATA
fujson-0.1.1.dist-info/WHEEL
fujson-0.1.1.dist-info/licenses/LICENSE.txt
fujson-0.1.1.dist-info/RECORD
