Metadata-Version: 2.1
Name: fujson
Version: 0.1.1
Summary: Float formatting control for JSON encoding.
Project-URL: Homepage, https://github.com/soxofaan/fujson
Project-URL: Bug Tracker, https://github.com/soxofaan/fujson/issues
Author-email: Stefaan Lippens <soxofaan@gmail.com>
License: MIT License
Classifier: License :: OSI Approved :: MIT License
Classifier: Operating System :: OS Independent
Classifier: Programming Language :: Python :: 3
Classifier: Programming Language :: Python :: 3.6
Classifier: Programming Language :: Python :: 3.7
Classifier: Programming Language :: Python :: 3.8
Classifier: Programming Language :: Python :: 3.9
Classifier: Programming Language :: Python :: 3.10
Classifier: Programming Language :: Python :: 3.11
Requires-Python: >=3.5
